contact_location_local/__init__.py
contact_location_local/contact_location_local.py
contact_location_local/contact_location_local_constants.py
contact_location_local-0.0.39.dist-info/METADATA
contact_location_local-0.0.39.dist-info/WHEEL
contact_location_local-0.0.39.dist-info/top_level.txt
contact_location_local-0.0.39.dist-info/RECORD
