Metadata-Version: 2.1
Name: contact-location-local
Version: 0.0.39
Summary: PyPI Package for Circles contact-location-local Python
Home-page: https://github.com/circles-zone/contact-location-local-python-package
Author: Circles
Author-email: info@circlez.ai
Classifier: Programming Language :: Python :: 3
Classifier: License :: Other/Proprietary License
Classifier: Operating System :: OS Independent
Requires-Dist: pycountry >=23.12.11
Requires-Dist: phonenumbers >=8.13.30
Requires-Dist: database-mysql-local >=0.0.342
Requires-Dist: group-local >=0.0.26
Requires-Dist: language-remote >=0.0.20
Requires-Dist: location-local >=0.0.119
Requires-Dist: logger-local >=0.0.135
Requires-Dist: user-context-remote >=0.0.57
Requires-Dist: contact-group-local >=0.0.58
